floodgate/__init__.py
floodgate/fastapi/__init__.py
floodgate/fastapi/guard.py
floodgate/flask/__init__.py
floodgate/flask/guard.py
floodgate/gates/__init__.py
floodgate/gates/catch_all.py
floodgate/gates/limit_strategies.py
floodgate/gates/units.py
floodgate/gates/util.py
floodgate-2.0.0.dist-info/LICENSE.txt
floodgate-2.0.0.dist-info/METADATA
floodgate-2.0.0.dist-info/WHEEL
floodgate-2.0.0.dist-info/top_level.txt
floodgate-2.0.0.dist-info/RECORD
