Metadata-Version: 2.1
Name: floodgate
Version: 2.0.0
Summary: Request rate limiter for Flask
Home-page: UNKNOWN
Author: Bhavesh Pareek
Author-email: bhavesh.pareek36@gmail.com
License: MIT
Platform: UNKNOWN
Provides-Extra: fastapi
Requires-Dist: fastapi ; extra == 'fastapi'
Provides-Extra: flask
Requires-Dist: Flask ; extra == 'flask'
